lttbc.cp310-win_amd64.pyd
lttbc-0.3.0.dist-info/LICENSE.txt
lttbc-0.3.0.dist-info/METADATA
lttbc-0.3.0.dist-info/WHEEL
lttbc-0.3.0.dist-info/top_level.txt
lttbc-0.3.0.dist-info/RECORD
