Metadata-Version: 2.1
Name: lttbc
Version: 0.3.0
Summary: Largest triangle three buckets module for Python written in C
Author-email: European XFEL GmbH <dennis.goeries@xfel.eu>
Maintainer-email: Dennis Goeries <dennis.goeries@xfel.eu>
License: MIT
Project-URL: git, https://github.com/dgoeries/lttbc
Classifier: Development Status :: 5 - Production/Stable
Classifier: Environment :: Console
Classifier: Intended Audience :: Developers
Classifier: Intended Audience :: Science/Research
Classifier: License :: OSI Approved :: MIT License
Classifier: Operating System :: OS Independent
Classifier: Programming Language :: Python :: 3
Classifier: Programming Language :: Python :: Implementation :: CPython
Classifier: Topic :: Scientific/Engineering :: Information Analysis
Classifier: Topic :: Scientific/Engineering :: Physics
Classifier: Topic :: Scientific/Engineering :: Visualization
Requires-Python: >=3.10
License-File: LICENSE.txt
Requires-Dist: numpy>=2.0
